Metadata-Version: 2.1
Name: Python-video-annotator-shaliulab
Version: 3.6.2
Home-page: https://bitbucket.org/fchampalimaud/pythonvideoannotator-models
Author: ['Ricardo Ribeiro']
Author-email: ricardojvr@gmail.com
